{
  "questions": [
    {
      "question": "The phenomenon of pollen grains germinating on the stigma of the same flower before it opens is called:",
      "difficulty": "medium",
      "pyq": true,
      "options": {
        "A": "Geitonogamy",
        "B": "Cleistogamy",
        "C": "Xenogamy",
        "D": "Autogamy"
      },
      "answer": "B",
      "tag": "pyq",
      "id": 1
    },
    {
      "question": "Embryo sac (female gametophyte) at maturity in Polygonum type is:",
      "difficulty": "hard",
      "pyq": true,
      "options": {
        "A": "4-nucleated",
        "B": "6-nucleated",
        "C": "8-nucleated, 7-celled",
        "D": "4-celled"
      },
      "answer": "C",
      "tag": "pyq",
      "id": 2
    },
    {
      "question": "The chalazal cells in an embryo sac are:",
      "difficulty": "hard",
      "pyq": true,
      "options": {
        "A": "Synergids",
        "B": "Antipodal cells",
        "C": "Polar nuclei",
        "D": "Egg cell"
      },
      "answer": "B",
      "tag": "pyq",
      "id": 3
    },
    {
      "question": "Exine of pollen grain is made up of:",
      "difficulty": "medium",
      "pyq": true,
      "options": {
        "A": "Cellulose",
        "B": "Pectin",
        "C": "Sporopollenin",
        "D": "Lignin"
      },
      "answer": "C",
      "tag": "pyq",
      "id": 4
    },
    {
      "question": "The process by which pollen grains are transferred from anther to stigma by wind is:",
      "difficulty": "medium",
      "pyq": true,
      "options": {
        "A": "Entomophily",
        "B": "Anemophily",
        "C": "Hydrophily",
        "D": "Ornithophily"
      },
      "answer": "B",
      "tag": "pyq",
      "id": 5
    },
    {
      "id": 6,
      "question": "Pollination that involves the transfer of pollen from anther to stigma of another flower of the same plant is ______.",
      "difficulty": "Medium",
      "hasDiagram": false,
      "diagram_description": "",
      "options": {
        "A": "Geitonogamy",
        "B": "Autogamy",
        "C": "Xenogamy",
        "D": "Cleistogamy"
      },
      "answer": "A"
    },
    {
      "id": 7,
      "question": "The only type of pollination which brings genetically different types of pollen grains to the stigma is ______.",
      "difficulty": "Medium",
      "hasDiagram": false,
      "diagram_description": "",
      "options": {
        "A": "Xenogamy",
        "B": "Autogamy",
        "C": "Geitonogamy",
        "D": "Chasmogamy"
      },
      "answer": "A"
    },
    {
      "id": 8,
      "question": "Flowers that never open, ensuring autogamy, are called ______.",
      "difficulty": "Medium",
      "hasDiagram": false,
      "diagram_description": "",
      "options": {
        "A": "Cleistogamous",
        "B": "Chasmogamous",
        "C": "Xenogamous",
        "D": "Emasculated"
      },
      "answer": "A"
    },
    {
      "id": 9,
      "question": "Pollination by wind is called ______.",
      "difficulty": "Medium",
      "hasDiagram": false,
      "diagram_description": "",
      "options": {
        "A": "Anemophily",
        "B": "Hydrophily",
        "C": "Entomophily",
        "D": "Zoophily"
      },
      "answer": "A"
    },
    {
      "id": 10,
      "question": "Triple fusion in angiosperms involves the fusion of one male gamete with ______.",
      "difficulty": "Medium",
      "hasDiagram": false,
      "diagram_description": "",
      "options": {
        "A": "Two polar nuclei (secondary nucleus)",
        "B": "Two antipodal cells",
        "C": "The egg cell",
        "D": "Synergids"
      },
      "answer": "A"
    },
    {
      "id": 11,
      "question": "Triple fusion results in the formation of ______.",
      "difficulty": "Medium",
      "hasDiagram": false,
      "diagram_description": "",
      "options": {
        "A": "Primary Endosperm Nucleus (PEN)",
        "B": "Zygote",
        "C": "Embryo",
        "D": "Seed coat"
      },
      "answer": "A"
    },
    {
      "id": 12,
      "question": "The coconut water from a tender coconut is actually ______.",
      "difficulty": "Hard",
      "hasDiagram": false,
      "diagram_description": "",
      "options": {
        "A": "Free-nuclear endosperm",
        "B": "Cellular endosperm",
        "C": "Mesocarp",
        "D": "Water from hilum"
      },
      "answer": "A"
    },
    {
      "id": 13,
      "question": "The part of the dicot embryo above the level of cotyledons is the ______.",
      "difficulty": "Medium",
      "hasDiagram": false,
      "diagram_description": "",
      "options": {
        "A": "Epicotyl",
        "B": "Hypocotyl",
        "C": "Radicle",
        "D": "Coleoptile"
      },
      "answer": "A"
    },
    {
      "id": 14,
      "question": "Epicotyl terminates with the ______ (stem tip).",
      "difficulty": "Medium",
      "hasDiagram": false,
      "diagram_description": "",
      "options": {
        "A": "Plumule",
        "B": "Radicle",
        "C": "Root cap",
        "D": "Coleorhiza"
      },
      "answer": "A"
    },
    {
      "id": 15,
      "question": "In monocots, the scutellum is the ______.",
      "difficulty": "Medium",
      "hasDiagram": false,
      "diagram_description": "",
      "options": {
        "A": "Single large cotyledon",
        "B": "Protective sheath of radicle",
        "C": "Undifferentiated sheath of plumule",
        "D": "Remnant of nucellus"
      },
      "answer": "A"
    },
    {
      "id": 16,
      "question": "Perisperm is the persistent ______ in seeds like black pepper and beet.",
      "difficulty": "Hard",
      "hasDiagram": false,
      "diagram_description": "",
      "options": {
        "A": "Nucellus",
        "B": "Endosperm",
        "C": "Embryo",
        "D": "Integument"
      },
      "answer": "A"
    },
    {
      "id": 17,
      "question": "Fruit developed without fertilisation is called ______.",
      "difficulty": "Medium",
      "hasDiagram": false,
      "diagram_description": "",
      "options": {
        "A": "Parthenocarpic fruit",
        "B": "False fruit",
        "C": "Polyembryony",
        "D": "Drupe"
      },
      "answer": "A"
    },
    {
      "id": 18,
      "question": "The production of seeds without fertilisation is called ______.",
      "difficulty": "Medium",
      "hasDiagram": false,
      "diagram_description": "",
      "options": {
        "A": "Apomixis",
        "B": "Parthenocarpy",
        "C": "Polyembryony",
        "D": "Cleistogamy"
      },
      "answer": "A"
    },
    {
      "id": 19,
      "question": "In which plants is polyembryony commonly seen?",
      "difficulty": "Medium",
      "hasDiagram": false,
      "diagram_description": "",
      "options": {
        "A": "Citrus and Mango",
        "B": "Pea and Bean",
        "C": "Rice and Wheat",
        "D": "Banana and Apple"
      },
      "answer": "A"
    },
    {
      "id": 20,
      "question": "Pollen grains of many species survive for months in ______.",
      "difficulty": "Hard",
      "hasDiagram": false,
      "diagram_description": "",
      "options": {
        "A": "Liquid nitrogen (-196°C)",
        "B": "Hot water",
        "C": "Soil",
        "D": "Normal refrigerators"
      },
      "answer": "A"
    }
  ]
}