{
  "questions": [
    {
      "id": 61,
      "question": "The power of a point P(x₁, y₁) with respect to circle S = 0 is ______.",
      "difficulty": "Medium",
      "hasDiagram": false,
      "diagram_description": "",
      "options": {
        "A": "S₁₁",
        "B": "√S₁₁",
        "C": "0",
        "D": "Radius"
      },
      "answer": "A"
    },
    {
      "id": 62,
      "question": "The length of tangent from (5,1) to circle x²+y²+6x−4y−3=0 is?",
      "difficulty": "Medium",
      "hasDiagram": false,
      "diagram_description": "",
      "options": {
        "A": "7",
        "B": "√37",
        "C": "5",
        "D": "√47"
      },
      "answer": "A",
      "pyq": true,
      "tag": "pyq"
    },
    {
      "id": 63,
      "question": "If the power of the point (1, 2) with respect to the circle x² + y² - 4x - 6y + k = 0 is 10, then k is ______.",
      "difficulty": "Medium",
      "hasDiagram": false,
      "diagram_description": "",
      "options": {
        "A": "25",
        "B": "15",
        "C": "-5",
        "D": "10"
      },
      "answer": "A"
    },
    {
      "id": 64,
      "question": "The condition for the line y = mx + c to be a tangent to the circle x² + y² = a² is ______.",
      "difficulty": "Medium",
      "hasDiagram": false,
      "diagram_description": "",
      "options": {
        "A": "c² = a²(1 + m²)",
        "B": "c = am",
        "C": "c² = a² / (1 + m²)",
        "D": "c = a"
      },
      "answer": "A"
    },
    {
      "id": 65,
      "question": "The coordinates of the point on the circle x² + y² - 2x - 4y - 20 = 0 which is farthest from the origin is ______.",
      "difficulty": "Hard",
      "hasDiagram": false,
      "diagram_description": "",
      "options": {
        "A": "(4, 6)",
        "B": "(2, 4)",
        "C": "(-1, -2)",
        "D": "(1, 2)"
      },
      "answer": "A"
    },
    {
      "id": 66,
      "question": "The length of the tangent from (1, 1) to the circle x² + y² + 4x + 4y - 1 = 0 is ______.",
      "difficulty": "Medium",
      "hasDiagram": false,
      "diagram_description": "",
      "options": {
        "A": "3",
        "B": "√7",
        "C": "4",
        "D": "√11"
      },
      "answer": "A"
    },
    {
      "id": 67,
      "question": "The radical axis of x² + y² - 4x - 6y - 12 = 0 and x² + y² + 6x + 18y + 26 = 0 is ______.",
      "difficulty": "Medium",
      "hasDiagram": false,
      "diagram_description": "",
      "options": {
        "A": "10x + 24y + 38 = 0",
        "B": "5x + 12y + 19 = 0",
        "C": "2x + 3y + 5 = 0",
        "D": "None"
      },
      "answer": "B"
    },
    {
      "id": 68,
      "question": "If the circle S₁ = 0 bisects the circumference of S₂ = 0, the common chord passes through the ______ of S₂.",
      "difficulty": "Medium",
      "hasDiagram": false,
      "diagram_description": "",
      "options": {
        "A": "Center",
        "B": "Origin",
        "C": "Focus",
        "D": "None"
      },
      "answer": "A"
    },
    {
      "id": 69,
      "question": "The equation of the circle whose diameter is the common chord of circles x² + y² = 4 and x² + y² + 2x + 2y + 1 = 0 is ______.",
      "difficulty": "Hard",
      "hasDiagram": false,
      "diagram_description": "",
      "options": {
        "A": "2(x² + y²) + 2x + 2y - 7 = 0",
        "B": "x² + y² + x + y = 0",
        "C": "x² + y² - x - y = 0",
        "D": "None"
      },
      "answer": "A"
    },
    {
      "id": 70,
      "question": "Minimum distance from a point P to a circle with center C and radius r is ______.",
      "difficulty": "Medium",
      "hasDiagram": false,
      "diagram_description": "",
      "options": {
        "A": "|CP - r|",
        "B": "CP + r",
        "C": "CP",
        "D": "r"
      },
      "answer": "A"
    },
    {
      "id": 71,
      "question": "The equation x² + y² + 2gx + 2fy + c = 0 represents a point circle if ______.",
      "difficulty": "Medium",
      "hasDiagram": false,
      "diagram_description": "",
      "options": {
        "A": "g² + f² - c = 0",
        "B": "g² + f² - c > 0",
        "C": "c = 0",
        "D": "g = f = 0"
      },
      "answer": "A"
    },
    {
      "id": 72,
      "question": "Two circles touch each other internally if the distance between centers is ______.",
      "difficulty": "Medium",
      "hasDiagram": false,
      "diagram_description": "",
      "options": {
        "A": "|r₁ - r₂|",
        "B": "r₁ + r₂",
        "C": "r₁ * r₂",
        "D": "r₁ / r₂"
      },
      "answer": "A"
    },
    {
      "id": 73,
      "question": "If two circles are orthogonal, the square of distance between centers is ______.",
      "difficulty": "Medium",
      "hasDiagram": false,
      "diagram_description": "",
      "options": {
        "A": "r₁² + r₂²",
        "B": "r₁² - r₂²",
        "C": "(r₁ + r₂)²",
        "D": "r₁ * r₂"
      },
      "answer": "A"
    },
    {
      "id": 74,
      "question": "The radius of the circle which touches the x-axis at (3, 0) and passes through (1, 2) is ______.",
      "difficulty": "Medium",
      "hasDiagram": false,
      "diagram_description": "",
      "options": {
        "A": "2",
        "B": "√2",
        "C": "3",
        "D": "√5"
      },
      "answer": "A"
    },
    {
      "id": 75,
      "question": "The length of the tangent from external point P(x₁, y₁) to circle S = 0 is ______.",
      "difficulty": "Medium",
      "hasDiagram": false,
      "diagram_description": "",
      "options": {
        "A": "√S₁₁",
        "B": "S₁₁",
        "C": "2√S₁₁",
        "D": "Radius"
      },
      "answer": "A"
    },
    {
      "id": 76,
      "question": "If line lx + my + n = 0 is a tangent to x² + y² = a², the point of contact is ______.",
      "difficulty": "Hard",
      "hasDiagram": false,
      "diagram_description": "",
      "options": {
        "A": "(-a²l/n, -a²m/n)",
        "B": "(a²l/n, a²m/n)",
        "C": "(-al/n, -am/n)",
        "D": "None"
      },
      "answer": "A"
    },
    {
      "id": 77,
      "question": "The equation of circle concentric with x²+y²−6x+4y+12=0 and passing through (−2,1)?",
      "difficulty": "Medium",
      "hasDiagram": false,
      "diagram_description": "",
      "options": {
        "A": "x²+y²−6x+4y−44=0",
        "B": "x²+y²−6x+4y+12=0",
        "C": "x²+y²−6x+4y−20=0",
        "D": "x²+y²−6x+4y=0"
      },
      "answer": "A",
      "pyq": true,
      "tag": "pyq"
    },
    {
      "id": 78,
      "question": "If a circle passes through point (a, b) and cuts x² + y² = k² orthogonally, its center locus is ______.",
      "difficulty": "Hard",
      "hasDiagram": false,
      "diagram_description": "",
      "options": {
        "A": "2ax + 2by - (a² + b² + k²) = 0",
        "B": "x² + y² = k²",
        "C": "ax + by = k²",
        "D": "None"
      },
      "answer": "A"
    },
    {
      "id": 79,
      "question": "Distance from origin to radical axis of x² + y² + 2x + 3y + 1 = 0 and x² + y² + 4x + 3y + 2 = 0 is ______.",
      "difficulty": "Hard",
      "hasDiagram": false,
      "diagram_description": "",
      "options": {
        "A": "1/2",
        "B": "1",
        "C": "2",
        "D": "0"
      },
      "answer": "A"
    },
    {
      "id": 80,
      "question": "The center of the circle which cuts the three circles x² + y² = 1, x² + y² - 2x = 3 and x² + y² - 2y = 3 orthogonally is ______.",
      "difficulty": "Hard",
      "hasDiagram": false,
      "diagram_description": "",
      "options": {
        "A": "(-1, -1)",
        "B": "(1, 1)",
        "C": "(0, 0)",
        "D": "(1, -1)"
      },
      "answer": "A"
    }
  ]
}