{
    "questions":  [
                      {
                          "id":  1,
                          "question":  "Interference? no. Replaced: energy is not destroyed at destructive interference point, just moved to constructive one.",
                          "difficulty":  "Medium",
                          "hasDiagram":  false,
                          "diagram_description":  "",
                          "options":  {
                                          "A":  "True",
                                          "B":  "False",
                                          "C":  "None",
                                          "D":  "None"
                                      },
                          "answer":  "A",
                          "pyq":  false
                      },
                      {
                          "id":  2,
                          "question":  "Dotted lines? no. Replaced: for thin films, path difference is 2 n t cos r.",
                          "difficulty":  "Hard",
                          "hasDiagram":  false,
                          "diagram_description":  "",
                          "options":  {
                                          "A":  "True",
                                          "B":  "False",
                                          "C":  "None",
                                          "D":  "None"
                                      },
                          "answer":  "A",
                          "pyq":  false
                      },
                      {
                          "question":  "A thin film of soap solution (n = 1.33) is illuminated by white light at normal incidence. If the film thickness is 5000 Å, the wavelength that will be absent in the reflected light is ______.",
                          "difficulty":  "Hard",
                          "options":  {
                                          "A":  "6650 Å",
                                          "B":  "4000 Å",
                                          "C":  "5000 Å",
                                          "D":  "6000 Å"
                                      },
                          "answer":  "A",
                          "hasDiagram":  false,
                          "diagram_description":  "None",
                          "pyq":  true,
                          "tag":  "hard",
                          "id":  3
                      },
                      {
                          "id":  4,
                          "question":  "Doppler effect in light? yes. shift in frequency due to relative motion.",
                          "difficulty":  "Medium",
                          "hasDiagram":  false,
                          "diagram_description":  "",
                          "options":  {
                                          "A":  "True",
                                          "B":  "False",
                                          "C":  "None",
                                          "D":  "None"
                                      },
                          "answer":  "A",
                          "pyq":  false
                      },
                      {
                          "question":  "In Young\u0027s double slit experiment, if the source is moved towards the slits, then the fringe width ______.",
                          "difficulty":  "Medium",
                          "options":  {
                                          "A":  "Remains unchanged",
                                          "B":  "Increases",
                                          "C":  "Decreases",
                                          "D":  "Becomes zero"
                                      },
                          "answer":  "A",
                          "hasDiagram":  false,
                          "diagram_description":  "None",
                          "pyq":  true,
                          "tag":  "hard",
                          "id":  5
                      },
                      {
                          "question":  "Which phenomenon confirms transverse nature of light?",
                          "difficulty":  "medium",
                          "pyq":  true,
                          "options":  {
                                          "A":  "Polarization",
                                          "B":  "Interference",
                                          "C":  "Diffraction",
                                          "D":  "Reflection"
                                      },
                          "answer":  "A",
                          "tag":  "pyq",
                          "id":  6
                      },
                      {
                          "question":  "In a single slit diffraction pattern, the distance between the first minima on either side of the central maximum is 5 mm. The screen is 1 m away and the slit width is 0.2 mm. The wavelength of light used is ______.",
                          "difficulty":  "Hard",
                          "options":  {
                                          "A":  "5000 Å",
                                          "B":  "6000 Å",
                                          "C":  "4000 Å",
                                          "D":  "7000 Å"
                                      },
                          "answer":  "A",
                          "hasDiagram":  false,
                          "diagram_description":  "None",
                          "pyq":  true,
                          "tag":  "hard",
                          "id":  7
                      },
                      {
                          "id":  8,
                          "question":  "Angular size of first minima? yes. λ / a.",
                          "difficulty":  "Medium",
                          "hasDiagram":  false,
                          "diagram_description":  "",
                          "options":  {
                                          "A":  "True",
                                          "B":  "False",
                                          "C":  "None",
                                          "D":  "None"
                                      },
                          "answer":  "A",
                          "pyq":  false
                      },
                      {
                          "id":  9,
                          "question":  "Numerical Aperture ? yes. n sin α.",
                          "difficulty":  "Hard",
                          "hasDiagram":  false,
                          "diagram_description":  "",
                          "options":  {
                                          "A":  "True",
                                          "B":  "False",
                                          "C":  "None",
                                          "D":  "None"
                                      },
                          "answer":  "A",
                          "pyq":  false
                      },
                      {
                          "question":  "When light of wavelength λ is incident on a surface, the Brewster angle is 60°. The refractive index of the surface is ______.",
                          "difficulty":  "Medium",
                          "options":  {
                                          "A":  "√3",
                                          "B":  "1/√3",
                                          "C":  "1.5",
                                          "D":  "1.33"
                                      },
                          "answer":  "A",
                          "hasDiagram":  false,
                          "diagram_description":  "None",
                          "pyq":  true,
                          "tag":  "hard",
                          "id":  10
                      },
                      {
                          "question":  "Two polaroids are placed in the path of unpolarized light such that no light is transmitted. The second polaroid is then rotated by 45°. The percentage of intensity of light transmitted now is ______.",
                          "difficulty":  "Hard",
                          "options":  {
                                          "A":  "25%",
                                          "B":  "50%",
                                          "C":  "12.5%",
                                          "D":  "100%"
                                      },
                          "answer":  "A",
                          "hasDiagram":  false,
                          "diagram_description":  "None",
                          "pyq":  true,
                          "tag":  "hard",
                          "id":  11
                      },
                      {
                          "id":  12,
                          "question":  "Diffraction? no. Replaced: central spot is dark in diffraction? no. it is brightest.",
                          "difficulty":  "Medium",
                          "hasDiagram":  false,
                          "diagram_description":  "",
                          "options":  {
                                          "A":  "True",
                                          "B":  "False",
                                          "C":  "None",
                                          "D":  "None"
                                      },
                          "answer":  "B",
                          "pyq":  false
                      },
                      {
                          "id":  13,
                          "question":  "Half-wave plate gives phase shift of π.",
                          "difficulty":  "Hard",
                          "hasDiagram":  false,
                          "diagram_description":  "",
                          "options":  {
                                          "A":  "True",
                                          "B":  "False",
                                          "C":  "None",
                                          "D":  "None"
                                      },
                          "answer":  "A",
                          "pyq":  false
                      },
                      {
                          "question":  "The diameter of the objective of a telescope is 0.1 m and the wavelength of light is 5000 Å. The resolving power of the telescope is ______.",
                          "difficulty":  "Hard",
                          "options":  {
                                          "A":  "1.64 x 10^5",
                                          "B":  "2 x 10^5",
                                          "C":  "1 x 10^5",
                                          "D":  "5 x 10^4"
                                      },
                          "answer":  "A",
                          "hasDiagram":  false,
                          "diagram_description":  "None",
                          "pyq":  true,
                          "tag":  "hard",
                          "id":  14
                      },
                      {
                          "question":  "In Young\u0027s double slit experiment, a transparent sheet of thickness t and refractive index n is placed in front of one of the slits. The central bright fringe shifts by ______.",
                          "difficulty":  "Medium",
                          "options":  {
                                          "A":  "(n-1)tD/d",
                                          "B":  "(n-1)t",
                                          "C":  "ntD/d",
                                          "D":  "(n-1)t/d"
                                      },
                          "answer":  "A",
                          "hasDiagram":  false,
                          "diagram_description":  "None",
                          "pyq":  true,
                          "tag":  "hard",
                          "id":  15
                      },
                      {
                          "id":  16,
                          "question":  "Red shift? yes. when source moves away from observer.",
                          "difficulty":  "Medium",
                          "hasDiagram":  false,
                          "diagram_description":  "",
                          "options":  {
                                          "A":  "True",
                                          "B":  "False",
                                          "C":  "None",
                                          "D":  "None"
                                      },
                          "answer":  "A",
                          "pyq":  false
                      },
                      {
                          "id":  17,
                          "question":  "Fresnel Biprism experiment? yes. used to find wavelength of light.",
                          "difficulty":  "Medium",
                          "hasDiagram":  false,
                          "diagram_description":  "",
                          "options":  {
                                          "A":  "True",
                                          "B":  "False",
                                          "C":  "None",
                                          "D":  "None"
                                      },
                          "answer":  "A",
                          "pyq":  false
                      },
                      {
                          "question":  "Two coherent sources of light have intensities in the ratio 81:1. The ratio of maximum to minimum intensity in their interference pattern is ______.",
                          "difficulty":  "Hard",
                          "options":  {
                                          "A":  "25:16",
                                          "B":  "10:8",
                                          "C":  "81:1",
                                          "D":  "9:1"
                                      },
                          "answer":  "A",
                          "hasDiagram":  false,
                          "diagram_description":  "None",
                          "pyq":  true,
                          "tag":  "hard",
                          "id":  18
                      },
                      {
                          "question":  "The angular width of the central maximum in a single slit diffraction pattern is 60°. The slit width is 1 μm. The wavelength of light used is ______.",
                          "difficulty":  "Hard",
                          "options":  {
                                          "A":  "5000 Å",
                                          "B":  "4000 Å",
                                          "C":  "6000 Å",
                                          "D":  "10000 Å"
                                      },
                          "answer":  "A",
                          "hasDiagram":  false,
                          "diagram_description":  "None",
                          "pyq":  true,
                          "tag":  "hard",
                          "id":  19
                      },
                      {
                          "id":  20,
                          "question":  "Diffraction? no. Replaced: secondary maxima intensity decreases with order.",
                          "difficulty":  "Medium",
                          "hasDiagram":  false,
                          "diagram_description":  "",
                          "options":  {
                                          "A":  "True",
                                          "B":  "False",
                                          "C":  "None",
                                          "D":  "None"
                                      },
                          "answer":  "A",
                          "pyq":  false
                      },
                      {
                          "id":  21,
                          "question":  "Circularly polarised light? yes. made of two perpendicular components with π/2 phase shift.",
                          "difficulty":  "Hard",
                          "hasDiagram":  false,
                          "diagram_description":  "",
                          "options":  {
                                          "A":  "True",
                                          "B":  "False",
                                          "C":  "None",
                                          "D":  "None"
                                      },
                          "answer":  "A",
                          "pyq":  false
                      },
                      {
                          "id":  22,
                          "question":  "Wave front? no. Replaced: if source is slit, wavefront is cylindrical.",
                          "difficulty":  "Medium",
                          "hasDiagram":  false,
                          "diagram_description":  "",
                          "options":  {
                                          "A":  "True",
                                          "B":  "False",
                                          "C":  "None",
                                          "D":  "None"
                                      },
                          "answer":  "A",
                          "pyq":  false
                      },
                      {
                          "question":  "Three polaroids P1, P2 and P3 are kept such that P1 and P3 are crossed. P2 is kept between them such that its axis is at 45° to P1. If unpolarized light of intensity I0 is incident on P1, the intensity of light emerging from P3 is ______.",
                          "difficulty":  "Hard",
                          "options":  {
                                          "A":  "I0/4",
                                          "B":  "I0/8",
                                          "C":  "I0/2",
                                          "D":  "Zero"
                                      },
                          "answer":  "B",
                          "hasDiagram":  false,
                          "diagram_description":  "None",
                          "pyq":  true,
                          "tag":  "hard",
                          "id":  23
                      },
                      {
                          "question":  "A galaxy is moving away from the earth with a speed of 300 km/s. The shift in wavelength for a spectral line of wavelength 6000 Å is ______.",
                          "difficulty":  "Medium",
                          "options":  {
                                          "A":  "6 Å",
                                          "B":  "0.6 Å",
                                          "C":  "60 Å",
                                          "D":  "3 Å"
                                      },
                          "answer":  "A",
                          "hasDiagram":  false,
                          "diagram_description":  "None",
                          "pyq":  true,
                          "tag":  "hard",
                          "id":  24
                      },
                      {
                          "question":  "In Young\u0027s double slit experiment, if the distance between the slits is halved and the distance between the slits and the screen is doubled, the fringe width becomes ______.",
                          "difficulty":  "Medium",
                          "options":  {
                                          "A":  "4 times",
                                          "B":  "Double",
                                          "C":  "Half",
                                          "D":  "Unchanged"
                                      },
                          "answer":  "A",
                          "hasDiagram":  false,
                          "diagram_description":  "None",
                          "pyq":  true,
                          "tag":  "hard",
                          "id":  25
                      }
                  ]
}
